conf.py
nick_derobertis_site/__init__.py
nick_derobertis_site/api/__init__.py
nick_derobertis_site/api/main.py
nick_derobertis_site/api/routers/__init__.py
nick_derobertis_site/api/routers/awards.py
nick_derobertis_site/api/routers/courses.py
nick_derobertis_site/api/routers/research.py
nick_derobertis_site/api/routers/skills.py
nick_derobertis_site/api/routers/software.py
nick_derobertis_site/api/routers/timeline.py
nick_derobertis_site/gen_content/__init__.py
nick_derobertis_site/gen_content/pdfs.py
nick_derobertis_site/logger.py
version.py
nick_derobertis_site-1.4.0.dist-info/WHEEL
nick_derobertis_site-1.4.0.dist-info/LICENSE.md
nick_derobertis_site-1.4.0.dist-info/METADATA
nick_derobertis_site-1.4.0.dist-info/RECORD
