Metadata-Version: 2.1
Name: nick-derobertis-site
Version: 1.4.0
Summary: Nick DeRobertis' Personal Website
License: MIT
Author: Nick DeRobertis
Author-email: whoopnip@gmail.com
Requires-Python: >=3.10
Classifier: Development Status :: 3 - Alpha
Classifier: Intended Audience :: Developers
Classifier: License :: OSI Approved :: MIT License
Classifier: Programming Language :: Python :: 3
Classifier: Programming Language :: Python :: 3.10
Classifier: Programming Language :: Python :: 3.11
Classifier: Programming Language :: Python :: 3.10
Classifier: Programming Language :: Python :: 3.11
Classifier: Programming Language :: Python :: 3.7
Classifier: Programming Language :: Python :: 3.8
Classifier: Programming Language :: Python :: 3.9
Requires-Dist: awesome-panel-extensions
Requires-Dist: derobertis-cv
Requires-Dist: fastapi
Requires-Dist: fire
Requires-Dist: jupyterlab
Requires-Dist: panel
Requires-Dist: pydantic
Requires-Dist: pydantic-to-typescript
Requires-Dist: sentry-sdk
Requires-Dist: uvicorn[standard]
Project-URL: documentation, https://nickderobertis.github.io/nick-derobertis-site
Project-URL: repository, https://github.com/nickderobertis/nick-derobertis-site
